[
    {
        "id": "moment1",
        "fileUrl": "images/moments/m (1).jpeg",
        "uploadedBy": "Loki",
        "uploadedAt": "2024-01-15T10:30:00Z",
        "fileName": "Her First Picture",
        "caption": "Her first picture when i see her for the first time",
        "rotation": -3
    },
    {
        "id": "moment2",
        "fileUrl": "images/moments/m (2).jpeg",
        "uploadedBy": "Loki",
        "uploadedAt": "2024-01-20T15:45:00Z",
        "fileName": "First outing",
        "caption": "Our first outing together",
        "rotation": 4
    },
    {
        "id": "moment3",
        "fileUrl": "images/moments/m (3).jpeg",
        "uploadedBy": "Loki",
        "uploadedAt": "2024-04-19T09:20:00Z",
        "fileName": "First outing",
        "caption": "Beautiful day with you",
        "rotation": -2
    },
    {
        "id": "moment4",
        "fileUrl": "images/moments/m (4).jpeg",
        "uploadedBy": "Crush",
        "uploadedAt": "2024-02-14T18:00:00Z",
        "fileName": "Your artwork",
        "caption": "Your amazing artwork that you shared with me",
        "rotation": 3
    },
    {
        "id": "moment5",
        "fileUrl": "images/moments/m (5).jpeg",
        "uploadedBy": "Loki",
        "uploadedAt": "2024-02-20T20:15:00Z",
        "fileName": "Memory",
        "caption": "A special memory we shared together",
        "rotation": -4
    },
    {
        "id": "moment6",
        "fileUrl": "images/moments/m (6).jpeg",
        "uploadedBy": "Crush",
        "uploadedAt": "2024-03-01T14:30:00Z",
        "fileName": "Chennai moments",
        "caption": "Long journey to Chennai with you",
        "rotation": 2
    },
    {
        "id": "moment7",
        "fileUrl": "images/moments/m (7).jpeg",
        "uploadedBy": "Loki5",
        "uploadedAt": "2026-01-21T11:20:00Z",
        "fileName": "Kiss",
        "caption": "Our first kiss captured in this moment",
        "rotation": -3
    },
    {
        "id": "moment8",
        "fileUrl": "images/moments/m (8).jpeg",
        "uploadedBy": "Loki1",
        "uploadedAt": "2024-03-10T16:45:00Z",
        "fileName": "Flower moment",
        "caption": "A beautiful moment with flowers",
        "rotation": 3
    },
    {
        "id": "moment9",
        "fileUrl": "images/moments/m (9).jpeg",
        "uploadedBy": "Loki2",
        "uploadedAt": "2026-01-21T07:50:00Z",
        "fileName": "Temple moment",
        "caption": "A beautiful moment at the temple",
        "rotation": 3
    },
    {
        "id": "moment10",
        "fileUrl": "images/moments/m (10).jpeg",
        "uploadedBy": "Loki3",
        "uploadedAt": "2026-01-21T07:50:00Z",
        "fileName": "Waiting moment",
        "caption": "A beautiful moment while waiting for Train",
        "rotation": 3
    },
    {
        "id": "moment11",
        "fileUrl": "images/moments/m (11).jpeg",
        "uploadedBy": "Loki4",
        "uploadedAt": "2026-01-21T07:50:00Z",
        "fileName": "Flower moment",
        "caption": "A beautiful moment with flowers",
        "rotation": 3
    },
    {
        "id": "moment12",
        "fileUrl": "images/moments/m (12).jpeg",
        "uploadedBy": "Loki",
        "uploadedAt": "2024-03-10T16:45:00Z",
        "fileName": "Mall",
        "caption": "A beautiful moment in mall",
        "rotation": 3
    },
    {
        "id": "moment13",
        "fileUrl": "images/moments/m (13).jpeg",
        "uploadedBy": "Loki",
        "uploadedAt": "2024-03-10T16:45:00Z",
        "fileName": "her sleeping moment",
        "caption": "A beautiful moment when she is sleeping in my shoulder",
        "rotation": 3
    },
    {
        "id": "moment14",
        "fileUrl": "images/moments/m (14).jpeg",
        "uploadedBy": "Loki",
        "uploadedAt": "2024-03-10T16:45:00Z",
        "fileName": "Flower moment",
        "caption": "A beautiful moment with flowers",
        "rotation": 3
    },
    {
        "id": "moment15",
        "fileUrl": "images/moments/m (15).jpeg",
        "uploadedBy": "Loki",
        "uploadedAt": "2024-03-10T16:45:00Z",
        "fileName": "Flower moment",
        "caption": "A beautiful moment with flowers",
        "rotation": 3
    },
    {
        "id": "moment16",
        "fileUrl": "images/moments/m (16).jpeg",
        "uploadedBy": "Loki",
        "uploadedAt": "2024-03-10T16:45:00Z",
        "fileName": "Flower moment",
        "caption": "A beautiful moment with flowers",
        "rotation": 3
    },
    {
        "id": "moment17",
        "fileUrl": "images/moments/m (17).jpeg",
        "uploadedBy": "Loki",
        "uploadedAt": "2024-03-10T16:45:00Z",
        "fileName": "Flower moment",
        "caption": "A beautiful moment with flowers",
        "rotation": 3
    },
    {
        "id": "moment18",
        "fileUrl": "images/moments/m (18).jpeg",
        "uploadedBy": "Loki",
        "uploadedAt": "2024-03-10T16:45:00Z",
        "fileName": "Flower moment",
        "caption": "A beautiful moment with flowers",
        "rotation": 3
    },
    {
        "id": "moment19",
        "fileUrl": "images/moments/m (19).jpeg",
        "uploadedBy": "Loki",
        "uploadedAt": "2024-03-10T16:45:00Z",
        "fileName": "Flower moment",
        "caption": "A beautiful moment with flowers",
        "rotation": 3
    },
    {
        "id": "moment20",
        "fileUrl": "images/moments/m (20).jpeg",
        "uploadedBy": "Loki",
        "uploadedAt": "2024-03-10T16:45:00Z",
        "fileName": "Flower moment",
        "caption": "A beautiful moment with flowers",
        "rotation": 3
    }
    
    
    
    
]